django_ibanfield/__init__.py
django_ibanfield/fields.py
django_ibanfield/serializers.py
django_ibanfield/validators.py
django_ibanfield-0.0.2.dist-info/LICENSE.txt
django_ibanfield-0.0.2.dist-info/METADATA
django_ibanfield-0.0.2.dist-info/WHEEL
django_ibanfield-0.0.2.dist-info/top_level.txt
django_ibanfield-0.0.2.dist-info/RECORD
