Metadata-Version: 2.1
Name: django-ibanfield
Version: 0.0.2
Summary: IBAN field for django with account validation
Home-page: https://github.com/KeoH/django-ibanfield
Author: Francisco Manzano Magaña
Author-email: keoh77@gmail.com
License: UNKNOWN
Platform: UNKNOWN
Classifier: Development Status :: 4 - Beta
Classifier: License :: OSI Approved :: GNU General Public License v3 (GPLv3)
Classifier: Natural Language :: Spanish
Classifier: Operating System :: OS Independent
Classifier: Programming Language :: Python :: 3
Classifier: Programming Language :: Python :: 3.6
Classifier: Programming Language :: Python :: 3.7
Provides-Extra: dev
Requires-Dist: pytest (>=5.4.1) ; extra == 'dev'
Requires-Dist: Django (>=2.2.10) ; extra == 'dev'
